keystamp/__init__.py
keystamp/__main__.py
keystamp/client/__init__.py
keystamp/client/auth.py
keystamp/client/interface.py
keystamp/client/local.py
keystamp/client/relay.py
keystamp/client/sign.py
keystamp/client/vault.py
keystamp/client/verify.py
keystamp/client/intercept/__init__.py
keystamp/client/intercept/base.py
keystamp/client/intercept/mpatch/__init__.py
keystamp/client/intercept/mpatch/core.py
keystamp/client/intercept/mpatch/iproxy.py
keystamp/resources/keys/README.md
keystamp/resources/keys/official-250204.pub
keystamp/server/__init__.py
keystamp/server/lambda_handler.py
keystamp-0.1.0.dist-info/METADATA
keystamp-0.1.0.dist-info/WHEEL
keystamp-0.1.0.dist-info/entry_points.txt
keystamp-0.1.0.dist-info/top_level.txt
keystamp-0.1.0.dist-info/RECORD
