Metadata-Version: 2.2
Name: keystamp
Version: 0.1.0
Summary: Cryptographic verification for LLM API interactions
Author-email: Keystamp <derekch@cs.stanford.edu>
License: MIT
Project-URL: Source, https://github.com/keystamp/keystamp
Classifier: Development Status :: 4 - Beta
Classifier: Intended Audience :: Science/Research
Classifier: License :: OSI Approved :: MIT License
Classifier: Programming Language :: Python :: 3
Classifier: Topic :: Scientific/Engineering :: Artificial Intelligence
Classifier: Topic :: Security :: Cryptography
Requires-Python: >=3.8
Requires-Dist: click>=8.1.8
Requires-Dist: mitmproxy>=11.0
Requires-Dist: cryptography>=44.0.0
Requires-Dist: typeguard>=4.4.1
Requires-Dist: loguru>=0.7.3
Requires-Dist: python-dotenv>=1.0.1
Requires-Dist: semver>=3.0.4
Requires-Dist: keystamp-common>=0.1.0
